{
  "_meta": {
    "source": "tpl_mtt_pot_reward_structure.lua",
    "format": "keys_bodys",
    "count": 29
  },
  "list": [
    {
      "id": 1,
      "min_cnt": 3,
      "max_cnt": 10,
      "reward_structure": "[ [1, 1, 7000], [2, 2, 3000] ]"
    },
    {
      "id": 2,
      "min_cnt": 11,
      "max_cnt": 20,
      "reward_structure": "[ [1, 1, 5000], [2, 2, 3000], [3, 3, 2000] ]"
    },
    {
      "id": 3,
      "min_cnt": 21,
      "max_cnt": 30,
      "reward_structure": "[ [1, 1, 3700], [2, 2, 2500], [3, 3, 1500], [4, 4, 1200], [5, 5, 1100] ]"
    },
    {
      "id": 4,
      "min_cnt": 31,
      "max_cnt": 40,
      "reward_structure": "[ [1, 1, 3500], [2, 2, 2200], [3, 3, 1500], [4, 4, 1100], [5, 5, 900], [6, 6, 800] ]"
    },
    {
      "id": 5,
      "min_cnt": 41,
      "max_cnt": 50,
      "reward_structure": "[ [1, 1, 3200], [2, 2, 1800], [3, 3, 1250], [4, 4, 1050], [5, 5, 830], [6, 6, 730], [7, 7, 620], [8, 8, 520] ]"
    },
    {
      "id": 6,
      "min_cnt": 51,
      "max_cnt": 60,
      "reward_structure": "[ [1, 1, 3000], [2, 2, 1750], [3, 3, 1220], [4, 4, 1020], [5, 5, 810], [6, 6, 710], [7, 7, 610], [8, 8, 510], [9, 9, 370] ]"
    },
    {
      "id": 7,
      "min_cnt": 61,
      "max_cnt": 75,
      "reward_structure": "[ [1, 1, 2900], [2, 2, 1700], [3, 3, 1200], [4, 4, 1000], [5, 5, 800], [6, 6, 690], [7, 7, 590], [8, 8, 490], [9, 9, 350], [10, 10, 280] ]"
    },
    {
      "id": 8,
      "min_cnt": 76,
      "max_cnt": 100,
      "reward_structure": "[ [1, 1, 2850], [2, 2, 1650], [3, 3, 1000], [4, 4, 800], [5, 5, 690], [6, 6, 590], [7, 7, 490], [8, 8, 380], [9, 9, 270], [10, 10, 230], [11, 15, 210] ]"
    },
    {
      "id": 9,
      "min_cnt": 101,
      "max_cnt": 125,
      "reward_structure": "[ [1, 1, 2800], [2, 2, 1620], [3, 3, 930], [4, 4, 730], [5, 5, 630], [6, 6, 530], [7, 7, 420], [8, 8, 300], [9, 9, 210], [10, 10, 180], [11, 15, 170], [16, 20, 160] ]"
    },
    {
      "id": 10,
      "min_cnt": 126,
      "max_cnt": 150,
      "reward_structure": "[ [1, 1, 2750], [2, 2, 1600], [3, 3, 910], [4, 4, 710], [5, 5, 610], [6, 6, 510], [7, 7, 390], [8, 8, 270], [9, 9, 180], [10, 10, 145], [11, 15, 135], [16, 20, 128], [21, 25, 122] ]"
    },
    {
      "id": 11,
      "min_cnt": 151,
      "max_cnt": 200,
      "reward_structure": "[ [1, 1, 2700], [2, 2, 1575], [3, 3, 900], [4, 4, 700], [5, 5, 600], [6, 6, 500], [7, 7, 380], [8, 8, 240], [9, 9, 170], [10, 10, 130], [11, 15, 120], [16, 20, 105], [21, 25, 100], [26, 30, 96] ]"
    },
    {
      "id": 12,
      "min_cnt": 201,
      "max_cnt": 250,
      "reward_structure": "[ [1, 1, 2650], [2, 2, 1550], [3, 3, 885], [4, 4, 680], [5, 5, 580], [6, 6, 480], [7, 7, 360], [8, 8, 240], [9, 9, 170], [10, 10, 130], [11, 15, 115], [16, 20, 100], [21, 25, 90], [26, 30, 80], [31, 35, 70] ]"
    },
    {
      "id": 13,
      "min_cnt": 251,
      "max_cnt": 300,
      "reward_structure": "[ [1, 1, 2600], [2, 2, 1500], [3, 3, 880], [4, 4, 680], [5, 5, 570], [6, 6, 470], [7, 7, 360], [8, 8, 240], [9, 9, 170], [10, 10, 130], [11, 15, 115], [16, 20, 100], [21, 25, 80], [26, 30, 70], [31, 35, 60], [36, 40, 55] ]"
    },
    {
      "id": 14,
      "min_cnt": 301,
      "max_cnt": 350,
      "reward_structure": "[ [1, 1, 2550], [2, 2, 1450], [3, 3, 860], [4, 4, 660], [5, 5, 560], [6, 6, 460], [7, 7, 350], [8, 8, 230], [9, 9, 160], [10, 10, 120], [11, 15, 105], [16, 20, 90], [21, 25, 70], [26, 30, 60], [31, 35, 53], [36, 40, 50], [41, 50, 46] ]"
    },
    {
      "id": 15,
      "min_cnt": 351,
      "max_cnt": 400,
      "reward_structure": "[ [1, 1, 2500], [2, 2, 1400], [3, 3, 850], [4, 4, 650], [5, 5, 550], [6, 6, 450], [7, 7, 340], [8, 8, 230], [9, 9, 150], [10, 10, 120], [11, 15, 100], [16, 20, 80], [21, 25, 64], [26, 30, 54], [31, 35, 45], [36, 40, 43], [41, 50, 42], [51, 60, 41] ]"
    },
    {
      "id": 16,
      "min_cnt": 401,
      "max_cnt": 500,
      "reward_structure": "[ [1, 1, 2440], [2, 2, 1375], [3, 3, 840], [4, 4, 640], [5, 5, 540], [6, 6, 440], [7, 7, 330], [8, 8, 220], [9, 9, 145], [10, 10, 110], [11, 15, 95], [16, 20, 75], [21, 25, 58], [26, 30, 48], [31, 35, 40], [36, 40, 36], [41, 50, 34], [51, 60, 33], [61, 75, 22] ]"
    },
    {
      "id": 17,
      "min_cnt": 501,
      "max_cnt": 600,
      "reward_structure": "[ [1, 1, 2400], [2, 2, 1270], [3, 3, 830], [4, 4, 630], [5, 5, 530], [6, 6, 430], [7, 7, 320], [8, 8, 210], [9, 9, 140], [10, 10, 110], [11, 15, 95], [16, 20, 75], [21, 25, 56], [26, 30, 45], [31, 35, 38], [36, 40, 34], [41, 50, 29], [51, 60, 27], [61, 75, 22], [76, 100, 21] ]"
    },
    {
      "id": 18,
      "min_cnt": 601,
      "max_cnt": 700,
      "reward_structure": "[ [1, 1, 2350], [2, 2, 1250], [3, 3, 820], [4, 4, 620], [5, 5, 520], [6, 6, 420], [7, 7, 310], [8, 8, 200], [9, 9, 140], [10, 10, 110], [11, 15, 90], [16, 20, 70], [21, 25, 51], [26, 30, 41], [31, 35, 33], [36, 40, 30], [41, 50, 25], [51, 60, 23], [61, 75, 22], [76, 100, 18], [101, 125, 17] ]"
    },
    {
      "id": 19,
      "min_cnt": 701,
      "max_cnt": 800,
      "reward_structure": "[ [1, 1, 2300], [2, 2, 1215], [3, 3, 800], [4, 4, 600], [5, 5, 500], [6, 6, 400], [7, 7, 290], [8, 8, 180], [9, 9, 130], [10, 10, 100], [11, 15, 85], [16, 20, 65], [21, 25, 45], [26, 30, 35], [31, 35, 30], [36, 40, 24], [41, 50, 23], [51, 60, 22], [61, 75, 21], [76, 100, 19], [101, 125, 17], [126, 150, 16] ]"
    },
    {
      "id": 20,
      "min_cnt": 801,
      "max_cnt": 900,
      "reward_structure": "[ [1, 1, 2250], [2, 2, 1170], [3, 3, 790], [4, 4, 590], [5, 5, 490], [6, 6, 390], [7, 7, 290], [8, 8, 180], [9, 9, 130], [10, 10, 100], [11, 15, 80], [16, 20, 60], [21, 25, 45], [26, 30, 34], [31, 35, 29], [36, 40, 22], [41, 50, 21], [51, 60, 20], [61, 75, 19], [76, 100, 18], [101, 125, 16], [126, 150, 15], [151, 175, 14] ]"
    },
    {
      "id": 21,
      "min_cnt": 901,
      "max_cnt": 1000,
      "reward_structure": "[ [1, 1, 2200], [2, 2, 1135], [3, 3, 790], [4, 4, 590], [5, 5, 490], [6, 6, 390], [7, 7, 290], [8, 8, 180], [9, 9, 130], [10, 10, 100], [11, 15, 80], [16, 20, 60], [21, 25, 43], [26, 30, 32], [31, 35, 27], [36, 40, 21], [41, 50, 20], [51, 60, 19], [61, 75, 18], [76, 100, 17], [101, 125, 15], [126, 150, 14], [151, 175, 12], [176, 200, 11] ]"
    },
    {
      "id": 22,
      "min_cnt": 1001,
      "max_cnt": 1250,
      "reward_structure": "[ [1, 1, 2150], [2, 2, 1110], [3, 3, 770], [4, 4, 570], [5, 5, 470], [6, 6, 370], [7, 7, 270], [8, 8, 160], [9, 9, 120], [10, 10, 90], [11, 15, 75], [16, 20, 60], [21, 25, 42], [26, 30, 31], [31, 35, 28], [36, 40, 21], [41, 50, 20], [51, 60, 19], [61, 75, 18], [76, 100, 17], [101, 125, 14], [126, 150, 14], [151, 175, 12], [176, 200, 11], [201, 225, 11] ]"
    },
    {
      "id": 23,
      "min_cnt": 1251,
      "max_cnt": 1500,
      "reward_structure": "[ [1, 1, 2100], [2, 2, 1100], [3, 3, 770], [4, 4, 570], [5, 5, 470], [6, 6, 370], [7, 7, 270], [8, 8, 160], [9, 9, 120], [10, 10, 90], [11, 15, 75], [16, 20, 58], [21, 25, 40], [26, 30, 30], [31, 35, 26], [36, 40, 20], [41, 50, 19], [51, 60, 18], [61, 75, 17], [76, 100, 16], [101, 125, 14], [126, 150, 12], [151, 175, 11], [176, 200, 11], [201, 225, 10], [226, 250, 10] ]"
    },
    {
      "id": 24,
      "min_cnt": 1501,
      "max_cnt": 1750,
      "reward_structure": "[ [1, 1, 2050], [2, 2, 1060], [3, 3, 770], [4, 4, 570], [5, 5, 470], [6, 6, 370], [7, 7, 270], [8, 8, 160], [9, 9, 120], [10, 10, 90], [11, 15, 75], [16, 20, 58], [21, 25, 40], [26, 30, 30], [31, 35, 26], [36, 40, 20], [41, 50, 19], [51, 60, 18], [61, 75, 17], [76, 100, 16], [101, 125, 12], [126, 150, 11], [151, 175, 11], [176, 200, 10], [201, 225, 10], [226, 250, 9], [251, 275, 9] ]"
    },
    {
      "id": 25,
      "min_cnt": 1751,
      "max_cnt": 2000,
      "reward_structure": "[ [1, 1, 2000], [2, 2, 1050], [3, 3, 770], [4, 4, 570], [5, 5, 470], [6, 6, 370], [7, 7, 270], [8, 8, 160], [9, 9, 120], [10, 10, 90], [11, 15, 75], [16, 20, 58], [21, 25, 40], [26, 30, 30], [31, 35, 26], [36, 40, 19], [41, 50, 18], [51, 60, 17], [61, 75, 16], [76, 100, 15], [101, 125, 12], [126, 150, 11], [151, 175, 10], [176, 200, 10], [201, 225, 9], [226, 250, 9], [251, 275, 8], [276, 300, 8] ]"
    },
    {
      "id": 26,
      "min_cnt": 2001,
      "max_cnt": 2250,
      "reward_structure": "[ [1, 1, 1950], [2, 2, 1015], [3, 3, 750], [4, 4, 550], [5, 5, 450], [6, 6, 350], [7, 7, 250], [8, 8, 140], [9, 9, 110], [10, 10, 85], [11, 15, 70], [16, 20, 55], [21, 25, 39], [26, 30, 29], [31, 35, 25], [36, 40, 19], [41, 50, 18], [51, 60, 17], [61, 75, 16], [76, 100, 15], [101, 125, 12], [126, 150, 11], [151, 175, 10], [176, 200, 9], [201, 225, 9], [226, 250, 8], [251, 275, 8], [276, 300, 7], [301, 350, 7] ]"
    },
    {
      "id": 27,
      "min_cnt": 2251,
      "max_cnt": 2500,
      "reward_structure": "[ [1, 1, 1900], [2, 2, 1005], [3, 3, 750], [4, 4, 550], [5, 5, 450], [6, 6, 350], [7, 7, 250], [8, 8, 140], [9, 9, 110], [10, 10, 85], [11, 15, 65], [16, 20, 52], [21, 25, 37], [26, 30, 27], [31, 35, 22], [36, 40, 18], [41, 50, 17], [51, 60, 16], [61, 75, 15], [76, 100, 14], [101, 125, 11], [126, 150, 10], [151, 175, 9], [176, 200, 9], [201, 225, 8], [226, 250, 8], [251, 275, 8], [276, 300, 7], [301, 350, 7], [351, 400, 6] ]"
    },
    {
      "id": 28,
      "min_cnt": 2501,
      "max_cnt": 2750,
      "reward_structure": "[ [1, 1, 1850], [2, 2, 980], [3, 3, 730], [4, 4, 530], [5, 5, 430], [6, 6, 330], [7, 7, 230], [8, 8, 120], [9, 9, 100], [10, 10, 75], [11, 15, 60], [16, 20, 47], [21, 25, 33], [26, 30, 24], [31, 35, 22], [36, 40, 18], [41, 50, 17], [51, 60, 16], [61, 75, 15], [76, 100, 14], [101, 125, 11], [126, 150, 10], [151, 175, 9], [176, 200, 9], [201, 225, 8], [226, 250, 8], [251, 275, 8], [276, 300, 7], [301, 350, 7], [351, 400, 6], [401, 450, 6] ]"
    },
    {
      "id": 29,
      "min_cnt": 2751,
      "max_cnt": 3000,
      "reward_structure": "[ [1, 1, 1800], [2, 2, 980], [3, 3, 730], [4, 4, 530], [5, 5, 430], [6, 6, 330], [7, 7, 230], [8, 8, 120], [9, 9, 100], [10, 10, 75], [11, 15, 65], [16, 20, 47], [21, 25, 33], [26, 30, 24], [31, 35, 22], [36, 40, 18], [41, 50, 17], [51, 60, 16], [61, 75, 15], [76, 100, 14], [101, 125, 11], [126, 150, 10], [151, 175, 9], [176, 200, 8], [201, 225, 8], [226, 250, 7], [251, 275, 7], [276, 300, 6], [301, 350, 6], [351, 400, 6], [401, 450, 5], [451, 500, 5] ]"
    }
  ],
  "map": {
    "1": {
      "id": 1,
      "min_cnt": 3,
      "max_cnt": 10,
      "reward_structure": "[ [1, 1, 7000], [2, 2, 3000] ]"
    },
    "2": {
      "id": 2,
      "min_cnt": 11,
      "max_cnt": 20,
      "reward_structure": "[ [1, 1, 5000], [2, 2, 3000], [3, 3, 2000] ]"
    },
    "3": {
      "id": 3,
      "min_cnt": 21,
      "max_cnt": 30,
      "reward_structure": "[ [1, 1, 3700], [2, 2, 2500], [3, 3, 1500], [4, 4, 1200], [5, 5, 1100] ]"
    },
    "4": {
      "id": 4,
      "min_cnt": 31,
      "max_cnt": 40,
      "reward_structure": "[ [1, 1, 3500], [2, 2, 2200], [3, 3, 1500], [4, 4, 1100], [5, 5, 900], [6, 6, 800] ]"
    },
    "5": {
      "id": 5,
      "min_cnt": 41,
      "max_cnt": 50,
      "reward_structure": "[ [1, 1, 3200], [2, 2, 1800], [3, 3, 1250], [4, 4, 1050], [5, 5, 830], [6, 6, 730], [7, 7, 620], [8, 8, 520] ]"
    },
    "6": {
      "id": 6,
      "min_cnt": 51,
      "max_cnt": 60,
      "reward_structure": "[ [1, 1, 3000], [2, 2, 1750], [3, 3, 1220], [4, 4, 1020], [5, 5, 810], [6, 6, 710], [7, 7, 610], [8, 8, 510], [9, 9, 370] ]"
    },
    "7": {
      "id": 7,
      "min_cnt": 61,
      "max_cnt": 75,
      "reward_structure": "[ [1, 1, 2900], [2, 2, 1700], [3, 3, 1200], [4, 4, 1000], [5, 5, 800], [6, 6, 690], [7, 7, 590], [8, 8, 490], [9, 9, 350], [10, 10, 280] ]"
    },
    "8": {
      "id": 8,
      "min_cnt": 76,
      "max_cnt": 100,
      "reward_structure": "[ [1, 1, 2850], [2, 2, 1650], [3, 3, 1000], [4, 4, 800], [5, 5, 690], [6, 6, 590], [7, 7, 490], [8, 8, 380], [9, 9, 270], [10, 10, 230], [11, 15, 210] ]"
    },
    "9": {
      "id": 9,
      "min_cnt": 101,
      "max_cnt": 125,
      "reward_structure": "[ [1, 1, 2800], [2, 2, 1620], [3, 3, 930], [4, 4, 730], [5, 5, 630], [6, 6, 530], [7, 7, 420], [8, 8, 300], [9, 9, 210], [10, 10, 180], [11, 15, 170], [16, 20, 160] ]"
    },
    "10": {
      "id": 10,
      "min_cnt": 126,
      "max_cnt": 150,
      "reward_structure": "[ [1, 1, 2750], [2, 2, 1600], [3, 3, 910], [4, 4, 710], [5, 5, 610], [6, 6, 510], [7, 7, 390], [8, 8, 270], [9, 9, 180], [10, 10, 145], [11, 15, 135], [16, 20, 128], [21, 25, 122] ]"
    },
    "11": {
      "id": 11,
      "min_cnt": 151,
      "max_cnt": 200,
      "reward_structure": "[ [1, 1, 2700], [2, 2, 1575], [3, 3, 900], [4, 4, 700], [5, 5, 600], [6, 6, 500], [7, 7, 380], [8, 8, 240], [9, 9, 170], [10, 10, 130], [11, 15, 120], [16, 20, 105], [21, 25, 100], [26, 30, 96] ]"
    },
    "12": {
      "id": 12,
      "min_cnt": 201,
      "max_cnt": 250,
      "reward_structure": "[ [1, 1, 2650], [2, 2, 1550], [3, 3, 885], [4, 4, 680], [5, 5, 580], [6, 6, 480], [7, 7, 360], [8, 8, 240], [9, 9, 170], [10, 10, 130], [11, 15, 115], [16, 20, 100], [21, 25, 90], [26, 30, 80], [31, 35, 70] ]"
    },
    "13": {
      "id": 13,
      "min_cnt": 251,
      "max_cnt": 300,
      "reward_structure": "[ [1, 1, 2600], [2, 2, 1500], [3, 3, 880], [4, 4, 680], [5, 5, 570], [6, 6, 470], [7, 7, 360], [8, 8, 240], [9, 9, 170], [10, 10, 130], [11, 15, 115], [16, 20, 100], [21, 25, 80], [26, 30, 70], [31, 35, 60], [36, 40, 55] ]"
    },
    "14": {
      "id": 14,
      "min_cnt": 301,
      "max_cnt": 350,
      "reward_structure": "[ [1, 1, 2550], [2, 2, 1450], [3, 3, 860], [4, 4, 660], [5, 5, 560], [6, 6, 460], [7, 7, 350], [8, 8, 230], [9, 9, 160], [10, 10, 120], [11, 15, 105], [16, 20, 90], [21, 25, 70], [26, 30, 60], [31, 35, 53], [36, 40, 50], [41, 50, 46] ]"
    },
    "15": {
      "id": 15,
      "min_cnt": 351,
      "max_cnt": 400,
      "reward_structure": "[ [1, 1, 2500], [2, 2, 1400], [3, 3, 850], [4, 4, 650], [5, 5, 550], [6, 6, 450], [7, 7, 340], [8, 8, 230], [9, 9, 150], [10, 10, 120], [11, 15, 100], [16, 20, 80], [21, 25, 64], [26, 30, 54], [31, 35, 45], [36, 40, 43], [41, 50, 42], [51, 60, 41] ]"
    },
    "16": {
      "id": 16,
      "min_cnt": 401,
      "max_cnt": 500,
      "reward_structure": "[ [1, 1, 2440], [2, 2, 1375], [3, 3, 840], [4, 4, 640], [5, 5, 540], [6, 6, 440], [7, 7, 330], [8, 8, 220], [9, 9, 145], [10, 10, 110], [11, 15, 95], [16, 20, 75], [21, 25, 58], [26, 30, 48], [31, 35, 40], [36, 40, 36], [41, 50, 34], [51, 60, 33], [61, 75, 22] ]"
    },
    "17": {
      "id": 17,
      "min_cnt": 501,
      "max_cnt": 600,
      "reward_structure": "[ [1, 1, 2400], [2, 2, 1270], [3, 3, 830], [4, 4, 630], [5, 5, 530], [6, 6, 430], [7, 7, 320], [8, 8, 210], [9, 9, 140], [10, 10, 110], [11, 15, 95], [16, 20, 75], [21, 25, 56], [26, 30, 45], [31, 35, 38], [36, 40, 34], [41, 50, 29], [51, 60, 27], [61, 75, 22], [76, 100, 21] ]"
    },
    "18": {
      "id": 18,
      "min_cnt": 601,
      "max_cnt": 700,
      "reward_structure": "[ [1, 1, 2350], [2, 2, 1250], [3, 3, 820], [4, 4, 620], [5, 5, 520], [6, 6, 420], [7, 7, 310], [8, 8, 200], [9, 9, 140], [10, 10, 110], [11, 15, 90], [16, 20, 70], [21, 25, 51], [26, 30, 41], [31, 35, 33], [36, 40, 30], [41, 50, 25], [51, 60, 23], [61, 75, 22], [76, 100, 18], [101, 125, 17] ]"
    },
    "19": {
      "id": 19,
      "min_cnt": 701,
      "max_cnt": 800,
      "reward_structure": "[ [1, 1, 2300], [2, 2, 1215], [3, 3, 800], [4, 4, 600], [5, 5, 500], [6, 6, 400], [7, 7, 290], [8, 8, 180], [9, 9, 130], [10, 10, 100], [11, 15, 85], [16, 20, 65], [21, 25, 45], [26, 30, 35], [31, 35, 30], [36, 40, 24], [41, 50, 23], [51, 60, 22], [61, 75, 21], [76, 100, 19], [101, 125, 17], [126, 150, 16] ]"
    },
    "20": {
      "id": 20,
      "min_cnt": 801,
      "max_cnt": 900,
      "reward_structure": "[ [1, 1, 2250], [2, 2, 1170], [3, 3, 790], [4, 4, 590], [5, 5, 490], [6, 6, 390], [7, 7, 290], [8, 8, 180], [9, 9, 130], [10, 10, 100], [11, 15, 80], [16, 20, 60], [21, 25, 45], [26, 30, 34], [31, 35, 29], [36, 40, 22], [41, 50, 21], [51, 60, 20], [61, 75, 19], [76, 100, 18], [101, 125, 16], [126, 150, 15], [151, 175, 14] ]"
    },
    "21": {
      "id": 21,
      "min_cnt": 901,
      "max_cnt": 1000,
      "reward_structure": "[ [1, 1, 2200], [2, 2, 1135], [3, 3, 790], [4, 4, 590], [5, 5, 490], [6, 6, 390], [7, 7, 290], [8, 8, 180], [9, 9, 130], [10, 10, 100], [11, 15, 80], [16, 20, 60], [21, 25, 43], [26, 30, 32], [31, 35, 27], [36, 40, 21], [41, 50, 20], [51, 60, 19], [61, 75, 18], [76, 100, 17], [101, 125, 15], [126, 150, 14], [151, 175, 12], [176, 200, 11] ]"
    },
    "22": {
      "id": 22,
      "min_cnt": 1001,
      "max_cnt": 1250,
      "reward_structure": "[ [1, 1, 2150], [2, 2, 1110], [3, 3, 770], [4, 4, 570], [5, 5, 470], [6, 6, 370], [7, 7, 270], [8, 8, 160], [9, 9, 120], [10, 10, 90], [11, 15, 75], [16, 20, 60], [21, 25, 42], [26, 30, 31], [31, 35, 28], [36, 40, 21], [41, 50, 20], [51, 60, 19], [61, 75, 18], [76, 100, 17], [101, 125, 14], [126, 150, 14], [151, 175, 12], [176, 200, 11], [201, 225, 11] ]"
    },
    "23": {
      "id": 23,
      "min_cnt": 1251,
      "max_cnt": 1500,
      "reward_structure": "[ [1, 1, 2100], [2, 2, 1100], [3, 3, 770], [4, 4, 570], [5, 5, 470], [6, 6, 370], [7, 7, 270], [8, 8, 160], [9, 9, 120], [10, 10, 90], [11, 15, 75], [16, 20, 58], [21, 25, 40], [26, 30, 30], [31, 35, 26], [36, 40, 20], [41, 50, 19], [51, 60, 18], [61, 75, 17], [76, 100, 16], [101, 125, 14], [126, 150, 12], [151, 175, 11], [176, 200, 11], [201, 225, 10], [226, 250, 10] ]"
    },
    "24": {
      "id": 24,
      "min_cnt": 1501,
      "max_cnt": 1750,
      "reward_structure": "[ [1, 1, 2050], [2, 2, 1060], [3, 3, 770], [4, 4, 570], [5, 5, 470], [6, 6, 370], [7, 7, 270], [8, 8, 160], [9, 9, 120], [10, 10, 90], [11, 15, 75], [16, 20, 58], [21, 25, 40], [26, 30, 30], [31, 35, 26], [36, 40, 20], [41, 50, 19], [51, 60, 18], [61, 75, 17], [76, 100, 16], [101, 125, 12], [126, 150, 11], [151, 175, 11], [176, 200, 10], [201, 225, 10], [226, 250, 9], [251, 275, 9] ]"
    },
    "25": {
      "id": 25,
      "min_cnt": 1751,
      "max_cnt": 2000,
      "reward_structure": "[ [1, 1, 2000], [2, 2, 1050], [3, 3, 770], [4, 4, 570], [5, 5, 470], [6, 6, 370], [7, 7, 270], [8, 8, 160], [9, 9, 120], [10, 10, 90], [11, 15, 75], [16, 20, 58], [21, 25, 40], [26, 30, 30], [31, 35, 26], [36, 40, 19], [41, 50, 18], [51, 60, 17], [61, 75, 16], [76, 100, 15], [101, 125, 12], [126, 150, 11], [151, 175, 10], [176, 200, 10], [201, 225, 9], [226, 250, 9], [251, 275, 8], [276, 300, 8] ]"
    },
    "26": {
      "id": 26,
      "min_cnt": 2001,
      "max_cnt": 2250,
      "reward_structure": "[ [1, 1, 1950], [2, 2, 1015], [3, 3, 750], [4, 4, 550], [5, 5, 450], [6, 6, 350], [7, 7, 250], [8, 8, 140], [9, 9, 110], [10, 10, 85], [11, 15, 70], [16, 20, 55], [21, 25, 39], [26, 30, 29], [31, 35, 25], [36, 40, 19], [41, 50, 18], [51, 60, 17], [61, 75, 16], [76, 100, 15], [101, 125, 12], [126, 150, 11], [151, 175, 10], [176, 200, 9], [201, 225, 9], [226, 250, 8], [251, 275, 8], [276, 300, 7], [301, 350, 7] ]"
    },
    "27": {
      "id": 27,
      "min_cnt": 2251,
      "max_cnt": 2500,
      "reward_structure": "[ [1, 1, 1900], [2, 2, 1005], [3, 3, 750], [4, 4, 550], [5, 5, 450], [6, 6, 350], [7, 7, 250], [8, 8, 140], [9, 9, 110], [10, 10, 85], [11, 15, 65], [16, 20, 52], [21, 25, 37], [26, 30, 27], [31, 35, 22], [36, 40, 18], [41, 50, 17], [51, 60, 16], [61, 75, 15], [76, 100, 14], [101, 125, 11], [126, 150, 10], [151, 175, 9], [176, 200, 9], [201, 225, 8], [226, 250, 8], [251, 275, 8], [276, 300, 7], [301, 350, 7], [351, 400, 6] ]"
    },
    "28": {
      "id": 28,
      "min_cnt": 2501,
      "max_cnt": 2750,
      "reward_structure": "[ [1, 1, 1850], [2, 2, 980], [3, 3, 730], [4, 4, 530], [5, 5, 430], [6, 6, 330], [7, 7, 230], [8, 8, 120], [9, 9, 100], [10, 10, 75], [11, 15, 60], [16, 20, 47], [21, 25, 33], [26, 30, 24], [31, 35, 22], [36, 40, 18], [41, 50, 17], [51, 60, 16], [61, 75, 15], [76, 100, 14], [101, 125, 11], [126, 150, 10], [151, 175, 9], [176, 200, 9], [201, 225, 8], [226, 250, 8], [251, 275, 8], [276, 300, 7], [301, 350, 7], [351, 400, 6], [401, 450, 6] ]"
    },
    "29": {
      "id": 29,
      "min_cnt": 2751,
      "max_cnt": 3000,
      "reward_structure": "[ [1, 1, 1800], [2, 2, 980], [3, 3, 730], [4, 4, 530], [5, 5, 430], [6, 6, 330], [7, 7, 230], [8, 8, 120], [9, 9, 100], [10, 10, 75], [11, 15, 65], [16, 20, 47], [21, 25, 33], [26, 30, 24], [31, 35, 22], [36, 40, 18], [41, 50, 17], [51, 60, 16], [61, 75, 15], [76, 100, 14], [101, 125, 11], [126, 150, 10], [151, 175, 9], [176, 200, 8], [201, 225, 8], [226, 250, 7], [251, 275, 7], [276, 300, 6], [301, 350, 6], [351, 400, 6], [401, 450, 5], [451, 500, 5] ]"
    }
  }
}